avro_helpers/__init__.py
avro_helpers/avro_converter_helpers.py
avro_helpers/avro_exceptions.py
avro_helpers/avro_general_helpers.py
avro_helpers/avro_reading_helpers.py
avro_helpers/avro_schema_helpers.py
avro_helpers/avro_writing_helpers.py
avro_helpers/tests/__init__.py
avro_helpers/tests/test_avro_converter_helpers.py
avro_helpers/tests/test_avro_exceptions.py
avro_helpers/tests/test_avro_general_helpers.py
avro_helpers/tests/test_avro_reading_helpers.py
avro_helpers/tests/test_avro_schema_helpers.py
avro_helpers/tests/test_avro_writing_helpers.py
ctodd_python_lib_avro-1.0.5.dist-info/LICENSE
ctodd_python_lib_avro-1.0.5.dist-info/METADATA
ctodd_python_lib_avro-1.0.5.dist-info/WHEEL
ctodd_python_lib_avro-1.0.5.dist-info/top_level.txt
ctodd_python_lib_avro-1.0.5.dist-info/RECORD
