Metadata-Version: 2.1
Name: ctodd-python-lib-avro
Version: 1.0.5
Summary: Python utilities used for interacting with .avro/.avsc files
Home-page: https://github.com/ChristopherHaydenTodd/ctodd-python-lib-avro
Author: Christopher H. Todd
Author-email: Christopher.Hayden.Todd@gmail.com
License: MIT
Keywords: python,libraries,avro,avsc
Platform: UNKNOWN
Classifier: Development Status :: 5 - Production/Stable
Classifier: Intended Audience :: Developers
Classifier: Natural Language :: English
Classifier: Programming Language :: Python
Classifier: Programming Language :: Python :: 3
Classifier: Programming Language :: Python :: 3.6
Classifier: Programming Language :: Python :: 3.7
Classifier: Programming Language :: Python :: 3.8
Requires-Python: >3.6
Requires-Dist: avro-python3 (>=1.8.2)
Requires-Dist: simplejson (>=3.16.0)
